tests/__init__.py
tests/api/__init__.py
tests/api/test_bma.py
tests/api/webserver.py
tests/api/bma/__init__.py
tests/api/bma/test_blockchain.py
tests/api/bma/test_network.py
tests/api/bma/test_tx.py
tests/api/bma/test_wot.py
tests/api/bma/test_ws.py
tests/documents/__init__.py
tests/documents/test_block.py
tests/documents/test_certification.py
tests/documents/test_membership.py
tests/documents/test_peer.py
tests/documents/test_transaction.py
tests/grammars/__init__.py
tests/grammars/test_output.py
ucoinpy/__init__.py
ucoinpy/api/__init__.py
ucoinpy/api/bma/__init__.py
ucoinpy/api/bma/api.py
ucoinpy/api/bma/blockchain.py
ucoinpy/api/bma/node.py
ucoinpy/api/bma/ud.py
ucoinpy/api/bma/wot.py
ucoinpy/api/bma/ws.py
ucoinpy/api/bma/network/__init__.py
ucoinpy/api/bma/network/peering.py
ucoinpy/api/bma/tx/__init__.py
ucoinpy/api/bma/tx/history.py
ucoinpy/documents/__init__.py
ucoinpy/documents/block.py
ucoinpy/documents/certification.py
ucoinpy/documents/constants.py
ucoinpy/documents/document.py
ucoinpy/documents/membership.py
ucoinpy/documents/peer.py
ucoinpy/documents/transaction.py
ucoinpy/grammars/__init__.py
ucoinpy/grammars/output.py
ucoinpy/key/__init__.py
ucoinpy/key/signing_key.py
ucoinpy-0.20.0.dist-info/DESCRIPTION.rst
ucoinpy-0.20.0.dist-info/METADATA
ucoinpy-0.20.0.dist-info/RECORD
ucoinpy-0.20.0.dist-info/WHEEL
ucoinpy-0.20.0.dist-info/metadata.json
ucoinpy-0.20.0.dist-info/top_level.txt
