Metadata-Version: 2.0
Name: ucoinpy
Version: 0.20.0
Summary: A python implementation of [uCoin](https://github.com/ucoin-io/ucoin) API
Home-page: https://github.com/ucoin-io/ucoin-python-api
Author: inso, canercanda, s_b
Author-email: insomniak.fr@gmail.com
License: UNKNOWN
Platform: UNKNOWN
Classifier: Programming Language :: Python
Classifier: Development Status :: 4 - Beta
Classifier: License :: OSI Approved :: GNU General Public License v3 (GPLv3)
Classifier: Natural Language :: French
Classifier: Operating System :: OS Independent
Classifier: Programming Language :: Python :: 3.5
Classifier: Topic :: Communications
Requires-Dist: aiohttp (>=0.19.0)
Requires-Dist: base58
Requires-Dist: jsonschema
Requires-Dist: libnacl
Requires-Dist: pylibscrypt
Requires-Dist: pypeg2
